Workbook
Name Slicer_Country: #N/A
Name Slicer_Product: #N/A

Sheet Shoe Sales
A1: Date | B1: Product | C1: Category | D1: Color | E1: Brand | F1: Country | G1: Quantity | H1: Unit Cost | I1: Unit Price
A2: 46023 | B2: derby | C2: FORMAL | D2: Black | E2: Clarks | F2: Nigeria | G2: 3 | H2: 110000 | I2: 111800
A3: 46024 | B3: CANVAS | C3: Casual | D3: Brown | E3: steve madden | F3: Uganda | G3: 8 | H3: 67000 | I3: 73500
A4: 46025 | B4: Slippers | C4: open | D4: Red | E4: NIKE | F4: Ghana | G4: 7 | H4: 44000 | I4: 49000
A5: 46026 | B5: loafers | C5: CASUAL | D5: Blue | E5: Zara | F5: UK | G5: 6 | H5: 73000 | I5: 76000
A6: 46027 | B6: BOOTS | C6: Utility | D6: Green | E6: timberland | F6: USA | G6: 14 | H6: 70000 | I6: 76500
A7: 46028 | B7: Oxford | C7: formal | D7: Black | E7: CLARKS | F7: Kenya | G7: 11 | H7: 118000 | I7: 119800
A8: 46029 | B8: brogues | C8: FORMAL | D8: Brown | E8: Clarks | F8: India | G8: 7 | H8: 86000 | I8: 87800
A9: 46030 | B9: MONK STRAPS | C9: Formal | D9: Red | E9: zara | F9: Germany | G9: 13 | H9: 124000 | I9: 125800
A10: 46031 | B10: Derby | C10: formal | D10: Blue | E10: CLARKS | F10: Albania | G10: 8 | H10: 136000 | I10: 137800
A11: 46031 | B11: Derby | C11: formal | D11: Blue | E11: CLARKS | F11: Albania | G11: 8 | H11: 136000 | I11: 137800
A12: 46032 | B12: canvas | C12: CASUAL | D12: Green | E12: Steve Madden | F12: Cyprus | G12: 12 | H12: 60000 | I12: 66000
A13: 46033 | B13: SLIPPERS | C13: Open | D13: Black | E13: nike | F13: Australia | G13: 9 | H13: 43000 | I13: 48000
... A501: 46497 | B501: monk straps | C501: FORMAL | D501: Brown | E501: Zara | F501: UK | G501: 2 | H501: 120000 | I501: 121800

Sheet Cleaned Data
A1: Date | B1: Product | C1: Category | D1: Color | E1: Brand | F1: Country | G1: Quantity | H1: Unit Cost | I1: Unit Price | J1: Revenue | K1: Cost | L1: Profit | M1: Profit Margin | N1: Sales Volume | O1: Product Category | P1: Performance level
A2: 46023 | B2: Derby | C2: Formal | D2: Black | E2: Clarks | F2: Nigeria | G2: 3 | H2: 110000 | I2: 111800 | J2: =PRODUCT('Cleaned Data'!$G2,'Cleaned Data'!$I2) -> 335400 | K2: =PRODUCT('Cleaned Data'!$G2,'Cleaned Data'!$H2) -> 330000 | L2: =('Cleaned Data'!$J2-'Cleaned Data'!$K2) -> 5400 | M2: =('Cleaned Data'!$L2/'Cleaned Data'!$J2) -> 0.016100179 | N2: =IF('Cleaned Data'!$G2>10,"High-Volume","Low-Volume") -> Low-Volume | O2: =IF('Cleaned Data'!$I2>=100000,"Premium","Standard") -> Premium | P2: =IF(Zen_Elite_Shoe_Sales[[#This Row],[Revenue]]>=1000000,"Top Performer","Average Performer") -> Average Performer | R2: Total Revenue | S2: =SUM(Zen_Elite_Shoe_Sales[Revenue]) -> 338533500
A3: 46024 | B3: Canvas | C3: Casual | D3: Brown | E3: Steve Madden | F3: Uganda | G3: 8 | H3: 67000 | I3: 73500 | J3: =PRODUCT('Cleaned Data'!$G3,'Cleaned Data'!$I3) -> 588000 | K3: =PRODUCT('Cleaned Data'!$G3,'Cleaned Data'!$H3) -> 536000 | L3: =('Cleaned Data'!$J3-'Cleaned Data'!$K3) -> 52000 | M3: =('Cleaned Data'!$L3/'Cleaned Data'!$J3) -> 0.088435374 | N3: =IF('Cleaned Data'!$G3>10,"High-Volume","Low-Volume") -> Low-Volume | O3: =IF('Cleaned Data'!$I3>=100000,"Premium","Standard") -> Standard | P3: =IF(Zen_Elite_Shoe_Sales[[#This Row],[Revenue]]>=1000000,"Top Performer","Average Performer") -> Average Performer
A4: 46025 | B4: Slippers | C4: Open | D4: Red | E4: Nike | F4: Ghana | G4: 7 | H4: 44000 | I4: 49000 | J4: =PRODUCT('Cleaned Data'!$G4,'Cleaned Data'!$I4) -> 343000 | K4: =PRODUCT('Cleaned Data'!$G4,'Cleaned Data'!$H4) -> 308000 | L4: =('Cleaned Data'!$J4-'Cleaned Data'!$K4) -> 35000 | M4: =('Cleaned Data'!$L4/'Cleaned Data'!$J4) -> 0.10204082 | N4: =IF('Cleaned Data'!$G4>10,"High-Volume","Low-Volume") -> Low-Volume | O4: =IF('Cleaned Data'!$I4>=100000,"Premium","Standard") -> Standard | P4: =IF(Zen_Elite_Shoe_Sales[[#This Row],[Revenue]]>=1000000,"Top Performer","Average Performer") -> Average Performer
A5: 46026 | B5: Loafers | C5: Casual | D5: Blue | E5: Zara | F5: UK | G5: 6 | H5: 73000 | I5: 76000 | J5: =PRODUCT('Cleaned Data'!$G5,'Cleaned Data'!$I5) -> 456000 | K5: =PRODUCT('Cleaned Data'!$G5,'Cleaned Data'!$H5) -> 438000 | L5: =('Cleaned Data'!$J5-'Cleaned Data'!$K5) -> 18000 | M5: =('Cleaned Data'!$L5/'Cleaned Data'!$J5) -> 0.039473684 | N5: =IF('Cleaned Data'!$G5>10,"High-Volume","Low-Volume") -> Low-Volume | O5: =IF('Cleaned Data'!$I5>=100000,"Premium","Standard") -> Standard | P5: =IF(Zen_Elite_Shoe_Sales[[#This Row],[Revenue]]>=1000000,"Top Performer","Average Performer") -> Average Performer
A6: 46027 | B6: Boots | C6: Utility | D6: Green | E6: Timberland | F6: USA | G6: 14 | H6: 70000 | I6: 76500 | J6: =PRODUCT('Cleaned Data'!$G6,'Cleaned Data'!$I6) -> 1071000 | K6: =PRODUCT('Cleaned Data'!$G6,'Cleaned Data'!$H6) -> 980000 | L6: =('Cleaned Data'!$J6-'Cleaned Data'!$K6) -> 91000 | M6: =('Cleaned Data'!$L6/'Cleaned Data'!$J6) -> 0.08496732 | N6: =IF('Cleaned Data'!$G6>10,"High-Volume","Low-Volume") -> High-Volume | O6: =IF('Cleaned Data'!$I6>=100000,"Premium","Standard") -> Standard | P6: =IF(Zen_Elite_Shoe_Sales[[#This Row],[Revenue]]>=1000000,"Top Performer","Average Performer") -> Top Performer | R6: Total Profit | S6: =SUM(L:L) -> 14155500
A7: 46028 | B7: Oxford | C7: Formal | D7: Black | E7: Clarks | F7: Kenya | G7: 11 | H7: 118000 | I7: 119800 | J7: =PRODUCT('Cleaned Data'!$G7,'Cleaned Data'!$I7) -> 1317800 | K7: =PRODUCT('Cleaned Data'!$G7,'Cleaned Data'!$H7) -> 1298000 | L7: =('Cleaned Data'!$J7-'Cleaned Data'!$K7) -> 19800 | M7: =('Cleaned Data'!$L7/'Cleaned Data'!$J7) -> 0.015025042 | N7: =IF('Cleaned Data'!$G7>10,"High-Volume","Low-Volume") -> High-Volume | O7: =IF('Cleaned Data'!$I7>=100000,"Premium","Standard") -> Premium | P7: =IF(Zen_Elite_Shoe_Sales[[#This Row],[Revenue]]>=1000000,"Top Performer","Average Performer") -> Top Performer
A8: 46029 | B8: Brogues | C8: Formal | D8: Brown | E8: Clarks | F8: India | G8: 7 | H8: 86000 | I8: 87800 | J8: =PRODUCT('Cleaned Data'!$G8,'Cleaned Data'!$I8) -> 614600 | K8: =PRODUCT('Cleaned Data'!$G8,'Cleaned Data'!$H8) -> 602000 | L8: =('Cleaned Data'!$J8-'Cleaned Data'!$K8) -> 12600 | M8: =('Cleaned Data'!$L8/'Cleaned Data'!$J8) -> 0.020501139 | N8: =IF('Cleaned Data'!$G8>10,"High-Volume","Low-Volume") -> Low-Volume | O8: =IF('Cleaned Data'!$I8>=100000,"Premium","Standard") -> Standard | P8: =IF(Zen_Elite_Shoe_Sales[[#This Row],[Revenue]]>=1000000,"Top Performer","Average Performer") -> Average Performer
A9: 46030 | B9: Monk Straps | C9: Formal | D9: Red | E9: Zara | F9: Germany | G9: 13 | H9: 124000 | I9: 125800 | J9: =PRODUCT('Cleaned Data'!$G9,'Cleaned Data'!$I9) -> 1635400 | K9: =PRODUCT('Cleaned Data'!$G9,'Cleaned Data'!$H9) -> 1612000 | L9: =('Cleaned Data'!$J9-'Cleaned Data'!$K9) -> 23400 | M9: =('Cleaned Data'!$L9/'Cleaned Data'!$J9) -> 0.014308426 | N9: =IF('Cleaned Data'!$G9>10,"High-Volume","Low-Volume") -> High-Volume | O9: =IF('Cleaned Data'!$I9>=100000,"Premium","Standard") -> Premium | P9: =IF(Zen_Elite_Shoe_Sales[[#This Row],[Revenue]]>=1000000,"Top Performer","Average Performer") -> Top Performer
A10: 46031 | B10: Derby | C10: Formal | D10: Blue | E10: Clarks | F10: Albania | G10: 8 | H10: 136000 | I10: 137800 | J10: =PRODUCT('Cleaned Data'!$G10,'Cleaned Data'!$I10) -> 1102400 | K10: =PRODUCT('Cleaned Data'!$G10,'Cleaned Data'!$H10) -> 1088000 | L10: =('Cleaned Data'!$J10-'Cleaned Data'!$K10) -> 14400 | M10: =('Cleaned Data'!$L10/'Cleaned Data'!$J10) -> 0.013062409 | N10: =IF('Cleaned Data'!$G10>10,"High-Volume","Low-Volume") -> Low-Volume | O10: =IF('Cleaned Data'!$I10>=100000,"Premium","Standard") -> Premium | P10: =IF(Zen_Elite_Shoe_Sales[[#This Row],[Revenue]]>=1000000,"Top Performer","Average Performer") -> Top Performer
A11: 46032 | B11: Canvas | C11: Casual | D11: Green | E11: Steve Madden | F11: Cyprus | G11: 12 | H11: 60000 | I11: 66000 | J11: =PRODUCT('Cleaned Data'!$G11,'Cleaned Data'!$I11) -> 792000 | K11: =PRODUCT('Cleaned Data'!$G11,'Cleaned Data'!$H11) -> 720000 | L11: =('Cleaned Data'!$J11-'Cleaned Data'!$K11) -> 72000 | M11: =('Cleaned Data'!$L11/'Cleaned Data'!$J11) -> 0.090909091 | N11: =IF('Cleaned Data'!$G11>10,"High-Volume","Low-Volume") -> High-Volume | O11: =IF('Cleaned Data'!$I11>=100000,"Premium","Standard") -> Standard | P11: =IF(Zen_Elite_Shoe_Sales[[#This Row],[Revenue]]>=1000000,"Top Performer","Average Performer") -> Average Performer
A12: 46033 | B12: Slippers | C12: Open | D12: Black | E12: Nike | F12: Australia | G12: 9 | H12: 43000 | I12: 48000 | J12: =PRODUCT('Cleaned Data'!$G12,'Cleaned Data'!$I12) -> 432000 | K12: =PRODUCT('Cleaned Data'!$G12,'Cleaned Data'!$H12) -> 387000 | L12: =('Cleaned Data'!$J12-'Cleaned Data'!$K12) -> 45000 | M12: =('Cleaned Data'!$L12/'Cleaned Data'!$J12) -> 0.10416667 | N12: =IF('Cleaned Data'!$G12>10,"High-Volume","Low-Volume") -> Low-Volume | O12: =IF('Cleaned Data'!$I12>=100000,"Premium","Standard") -> Standard | P12: =IF(Zen_Elite_Shoe_Sales[[#This Row],[Revenue]]>=1000000,"Top Performer","Average Performer") -> Average Performer
A13: 46034 | B13: Loafers | C13: Casual | D13: Brown | E13: Zara | F13: Canada | G13: 6 | H13: 72000 | I13: 75000 | J13: =PRODUCT('Cleaned Data'!$G13,'Cleaned Data'!$I13) -> 450000 | K13: =PRODUCT('Cleaned Data'!$G13,'Cleaned Data'!$H13) -> 432000 | L13: =('Cleaned Data'!$J13-'Cleaned Data'!$K13) -> 18000 | M13: =('Cleaned Data'!$L13/'Cleaned Data'!$J13) -> 0.04 | N13: =IF('Cleaned Data'!$G13>10,"High-Volume","Low-Volume") -> Low-Volume | O13: =IF('Cleaned Data'!$I13>=100000,"Premium","Standard") -> Standard | P13: =IF(Zen_Elite_Shoe_Sales[[#This Row],[Revenue]]>=1000000,"Top Performer","Average Performer") -> Average Performer
A14: 46035 | B14: Boots | C14: Utility | D14: Red | E14: Timberland | F14: Philippines | G14: 6 | H14: 58000 | I14: 64000 | J14: =PRODUCT('Cleaned Data'!$G14,'Cleaned Data'!$I14) -> 384000 | K14: =PRODUCT('Cleaned Data'!$G14,'Cleaned Data'!$H14) -> 348000 | L14: =('Cleaned Data'!$J14-'Cleaned Data'!$K14) -> 36000 | M14: =('Cleaned Data'!$L14/'Cleaned Data'!$J14) -> 0.09375 | N14: =IF('Cleaned Data'!$G14>10,"High-Volume","Low-Volume") -> Low-Volume | O14: =IF('Cleaned Data'!$I14>=100000,"Premium","Standard") -> Standard | P14: =IF(Zen_Elite_Shoe_Sales[[#This Row],[Revenue]]>=1000000,"Top Performer","Average Performer") -> Average Performer
A15: 46036 | B15: Oxford | C15: Formal | D15: Blue | E15: Clarks | F15: Zimbabwe | G15: 3 | H15: 93000 | I15: 94800 | J15: =PRODUCT('Cleaned Data'!$G15,'Cleaned Data'!$I15) -> 284400 | K15: =PRODUCT('Cleaned Data'!$G15,'Cleaned Data'!$H15) -> 279000 | L15: =('Cleaned Data'!$J15-'Cleaned Data'!$K15) -> 5400 | M15: =('Cleaned Data'!$L15/'Cleaned Data'!$J15) -> 0.018987342 | N15: =IF('Cleaned Data'!$G15>10,"High-Volume","Low-Volume") -> Low-Volume | O15: =IF('Cleaned Data'!$I15>=100000,"Premium","Standard") -> Standard | P15: =IF(Zen_Elite_Shoe_Sales[[#This Row],[Revenue]]>=1000000,"Top Performer","Average Performer") -> Average Performer
A16: 46037 | B16: Brogues | C16: Formal | D16: Green | E16: Clarks | F16: Nigeria | G16: 11 | H16: 96000 | I16: 97800 | J16: =PRODUCT('Cleaned Data'!$G16,'Cleaned Data'!$I16) -> 1075800 | K16: =PRODUCT('Cleaned Data'!$G16,'Cleaned Data'!$H16) -> 1056000 | L16: =('Cleaned Data'!$J16-'Cleaned Data'!$K16) -> 19800 | M16: =('Cleaned Data'!$L16/'Cleaned Data'!$J16) -> 0.018404908 | N16: =IF('Cleaned Data'!$G16>10,"High-Volume","Low-Volume") -> High-Volume | O16: =IF('Cleaned Data'!$I16>=100000,"Premium","Standard") -> Standard | P16: =IF(Zen_Elite_Shoe_Sales[[#This Row],[Revenue]]>=1000000,"Top Performer","Average Performer") -> Top Performer
A17: 46038 | B17: Monk Straps | C17: Formal | D17: Black | E17: Zara | F17: Uganda | G17: 7 | H17: 135000 | I17: 136800 | J17: =PRODUCT('Cleaned Data'!$G17,'Cleaned Data'!$I17) -> 957600 | K17: =PRODUCT('Cleaned Data'!$G17,'Cleaned Data'!$H17) -> 945000 | L17: =('Cleaned Data'!$J17-'Cleaned Data'!$K17) -> 12600 | M17: =('Cleaned Data'!$L17/'Cleaned Data'!$J17) -> 0.013157895 | N17: =IF('Cleaned Data'!$G17>10,"High-Volume","Low-Volume") -> Low-Volume | O17: =IF('Cleaned Data'!$I17>=100000,"Premium","Standard") -> Premium | P17: =IF(Zen_Elite_Shoe_Sales[[#This Row],[Revenue]]>=1000000,"Top Performer","Average Performer") -> Average Performer
A18: 46039 | B18: Derby | C18: Formal | D18: Brown | E18: Clarks | F18: Ghana | G18: 13 | H18: 105000 | I18: 106800 | J18: =PRODUCT('Cleaned Data'!$G18,'Cleaned Data'!$I18) -> 1388400 | K18: =PRODUCT('Cleaned Data'!$G18,'Cleaned Data'!$H18) -> 1365000 | L18: =('Cleaned Data'!$J18-'Cleaned Data'!$K18) -> 23400 | M18: =('Cleaned Data'!$L18/'Cleaned Data'!$J18) -> 0.016853933 | N18: =IF('Cleaned Data'!$G18>10,"High-Volume","Low-Volume") -> High-Volume | O18: =IF('Cleaned Data'!$I18>=100000,"Premium","Standard") -> Premium | P18: =IF(Zen_Elite_Shoe_Sales[[#This Row],[Revenue]]>=1000000,"Top Performer","Average Performer") -> Top Performer
... A476: 46497 | B476: Monk Straps | C476: Formal | D476: Brown | E476: Zara | F476: UK | G476: 2 | H476: 120000 | I476: 121800 | J476: =PRODUCT('Cleaned Data'!$G476,'Cleaned Data'!$I476) -> 243600 | K476: =PRODUCT('Cleaned Data'!$G476,'Cleaned Data'!$H476) -> 240000 | L476: =('Cleaned Data'!$J476-'Cleaned Data'!$K476) -> 3600 | M476: =('Cleaned Data'!$L476/'Cleaned Data'!$J476) -> 0.014778325 | N476: =IF('Cleaned Data'!$G476>10,"High-Volume","Low-Volume") -> Low-Volume | O476: =IF('Cleaned Data'!$I476>=100000,"Premium","Standard") -> Premium | P476: =IF(Zen_Elite_Shoe_Sales[[#This Row],[Revenue]]>=1000000,"Top Performer","Average Performer") -> Average Performer

Sheet Pivot Analysis
B1: KPIs
B2: Total Revenue | C2: total Cost | D2: Total Profit | E2: Total Quantity Sold | F2: Average Profit Margin
B3: 338533500 | C3: 324378000 | D3: 14155500 | E3: 3825 | F3: 0.051812327
B7: Country | C7: Revenue | F7: Country | G7: Profit | J7: Product | K7: Revenue | N7: Product | O7: Profit | R7: Category | S7: Revenue | V7: Brand | W7: Total Quantity Sold | Z7: Product Category | AA7: Revenue | AC7: Product | AD7: Count of Profit Margin
B8: Uganda | C8: 29283200 | F8: UK | G8: 1191100 | J8: Monk Straps | K8: 62057800 | N8: Canvas | O8: 2924500 | R8: Formal | S8: 214210000 | V8: Steve Madden | W8: 522 | Z8: Premium | AA8: 186690400 | AC8: Boots | AD8: 60
B9: UK | C9: 28419100 | F9: Canada | G9: 1166900 | J9: Derby | K9: 53660400 | N9: Slippers | O9: 2709000 | R9: Casual | S9: 61979000 | V9: Timberland | W9: 553 | Z9: Standard | AA9: 151843100 | AC9: Brogues | AD9: 57
B10: Kenya | C10: 26676000 | F10: Zimbabwe | G10: 1151200 | J10: Oxford | K10: 52999600 | N10: Boots | O10: 2675500 | R10: Utility | S10: 35628500 | V10: Nike | W10: 614 | Z10: Grand Total | AA10: 338533500 | AC10: Canvas | AD10: 60
B11: Philippines | C11: 25040200 | F11: Kenya | G11: 1125000 | J11: Brogues | K11: 45492200 | N11: Loafers | O11: 2462500 | R11: Open | S11: 26716000 | V11: Zara | W11: 924 | AC11: Derby | AD11: 62
B12: Zimbabwe | C12: 24937200 | F12: Nigeria | G12: 1120500 | J12: Boots | K12: 35628500 | N12: Monk Straps | O12: 919800 | R12: Grand Total | S12: 338533500 | V12: Clarks | W12: 1212 | AC12: Loafers | AD12: 49
B13: USA | C13: 24743800 | F13: Australia | G13: 1064900 | J13: Canvas | K13: 31233500 | N13: Oxford | O13: 876600 | V13: Grand Total | W13: 3825 | Z13: Product Category | AA13: Quantity Sold | AC13: Monk Straps | AD13: 61
B14: Ghana | C14: 24377400 | F14: Uganda | G14: 1035200 | J14: Loafers | K14: 30745500 | N14: Derby | O14: 797400 | Z14: High-Volume | AA14: 1908 | AC14: Oxford | AD14: 60
B15: Cyprus | C15: 24263100 | F15: USA | G15: 1034800 | J15: Slippers | K15: 26716000 | N15: Brogues | O15: 790200 | R15: Category | S15: Profit | Z15: Low-Volume | AA15: 1917 | AC15: Slippers | AD15: 66
B16: Nigeria | C16: 23010500 | F16: Philippines | G16: 1016200 | J16: Grand Total | K16: 338533500 | N16: Grand Total | O16: 14155500 | R16: Casual | S16: 5387000 | Z16: Grand Total | AA16: 3825 | AC16: Grand Total | AD16: 475
B17: India | C17: 22482200 | F17: Ghana | G17: 979400 | R17: Formal | S17: 3384000
B18: Albania | C18: 22206900 | F18: Cyprus | G18: 852100 | R18: Open | S18: 2709000
B19: Canada | C19: 21397900 | F19: Germany | G19: 820100 | R19: Utility | S19: 2675500
B20: Australia | C20: 21209900 | F20: India | G20: 812200 | R20: Grand Total | S20: 14155500
B21: Germany | C21: 20486100 | F21: Albania | G21: 785900
B22: Grand Total | C22: 338533500 | F22: Grand Total | G22: 14155500

Sheet Insights
A1: From the analysis done on the analysis sheet, the following insights were deduced:
A3: Project Insights
A4: 1. Total Revenue generated by the business :
B5: 338533500
A7: 2.Total profit generated:
B8: 14155500
A10: 3. Country that generated the highest Revenue: Uganda
A12: 4. Strongest Performing Country by Profit:
B13: UK is the strongest-performing country by profit with the highest profit of #1,191.100 . This indicates that there is a high customer demand and a strong market performance in that region.
A15: 5. Strongest Performing Product by Revenue:
B16: Monk Straps generated the highest revenue of #62,057,800 among all products and also among the top 5 products with the highest profit. Making it the strongest performing product overall.
A18: 6. Most Profitable Product:
B19: The most profitable product is canvas with a profit of #2,924,500.
A21: 7. Category that contributed the most to Revenue:
B22: The Formal Category contributed the most to the total revenue. Contributing the sum of #214,210,000 to the toatal sum of #338,533,500 as revenue. This makes up 63.3% of the total revenue
A24: 8. Brand with the highest quantity sold:
B25: Clarks sold the highest quantity of 1,212.
A27: 9. Transaction type:
B28: According to the Pivot Analysis, most transaction are low-volume sales as low-volume sale have a total quantity of 1,917 out of the total quantity of 3,825 sold.
A30: 10. Premium vs Standard:
B31: Premium products generated more revenue with a 55% revenue generation.
A33: 11. Products that require pricing or cost review:
B34: According to my analysis, Monks Straps, Derby, Oxford and Brogues all have very high revenue but relatively low profits. This shows that they have high market demand but may require better pricing or cost review.

Sheet Dashboard
E1: Zen EliteStride Maison Shoe Sales Dashboard 2026

Sheet Business Recommendation
A1: Reccomendations to Managements
B3: 1. Increase focus and marketing investment in high-performing countries like UK and Uganda to maximize revenue opportunities.
B5: 2. Promote high-profit products like canvas and high categories products such as Formal footwear.
B7: 3. Review pricing and operational costs for low-profit products to improve profitability.
B9: 4. Improve marketing strategies for weak-performing products and countries to increase customer engagement and sales.
B11: 5. Monitor discount strategies carefully to avoid reducing overall profit margins.
B13: 6. Expand premium product offerings since they contribute more revenue and profit to the business.
